Brand_Peeker/__init__.py
Brand_Peeker/getUrls.py
Brand_Peeker/main.py
Brand_Peeker/tryBrandPeeker.py
Brand_Peeker-0.2.2.dist-info/LICENSE
Brand_Peeker-0.2.2.dist-info/METADATA
Brand_Peeker-0.2.2.dist-info/WHEEL
Brand_Peeker-0.2.2.dist-info/top_level.txt
Brand_Peeker-0.2.2.dist-info/RECORD
