Metadata-Version: 2.2
Name: Brand_Peeker
Version: 0.2.2
Summary: A python library that allows you to scrape information about a brand, such as its logo or website
Home-page: https://github.com/GazButane/Brand_Peeker
Author: Gaz_Butane
Classifier: Programming Language :: Python :: 3
Classifier: License :: OSI Approved :: MIT License
Classifier: Operating System :: OS Independent
Requires-Python: >=3.0
License-File: LICENSE
Requires-Dist: asgiref==3.8.1
Requires-Dist: beautifulsoup4==4.13.3
Requires-Dist: certifi==2025.1.31
Requires-Dist: charset-normalizer==3.4.1
Requires-Dist: django-googlesearch==0.2
Requires-Dist: idna==3.10
Requires-Dist: lxml==5.3.1
Requires-Dist: requests==2.32.3
Requires-Dist: soupsieve==2.6
Requires-Dist: sqlparse==0.5.3
Requires-Dist: typing_extensions==4.12.2
Requires-Dist: urllib3==2.3.0
Requires-Dist: validators==0.34.0
Dynamic: author
Dynamic: classifier
Dynamic: description
Dynamic: description-content-type
Dynamic: home-page
Dynamic: requires-dist
Dynamic: requires-python
Dynamic: summary
